calzone/__init__.py
calzone/__main__.py
calzone/_core.abi3.so
calzone.libs/libG4analysis-67a0c50f.so
calzone.libs/libG4clhep-315323a3.so
calzone.libs/libG4digits_hits-2dab33cd.so
calzone.libs/libG4event-60e795de.so
calzone.libs/libG4geometry-5609993a.so
calzone.libs/libG4global-bd925847.so
calzone.libs/libG4graphics_reps-9e623a4b.so
calzone.libs/libG4intercoms-cfe1bcfa.so
calzone.libs/libG4materials-11d64b03.so
calzone.libs/libG4parmodels-d8d980fe.so
calzone.libs/libG4particles-27c03ac5.so
calzone.libs/libG4physicslists-eb132205.so
calzone.libs/libG4processes-a2ada4bc.so
calzone.libs/libG4ptl-bcdf3b20.so.3.0.0
calzone.libs/libG4run-4365fa21.so
calzone.libs/libG4track-b00671d9.so
calzone.libs/libG4tracking-937d0b59.so
calzone.libs/libG4zlib-e2cda8fc.so
calzone-1.1.6.dist-info/COPYING.LESSER
calzone-1.1.6.dist-info/LICENSE
calzone-1.1.6.dist-info/METADATA
calzone-1.1.6.dist-info/WHEEL
calzone-1.1.6.dist-info/entry_points.txt
calzone-1.1.6.dist-info/top_level.txt
calzone-1.1.6.dist-info/RECORD
