Metadata-Version: 2.1
Name: calzone
Version: 1.1.6
Summary: A Geant4 Python wrapper.
Author-email: Valentin Niess <valentin.niess@gmail.com>
License: LGPLv3
Project-URL: source, https://github.com/niess/calzone
Keywords: Python,Monte Carlo,Geant4
Classifier: Intended Audience :: Science/Research
Classifier: Topic :: Scientific/Engineering :: Physics
Requires-Python: >=3.7.0
License-File: LICENSE
License-File: COPYING.LESSER
Requires-Dist: numpy >=1.6.0
